HDL/SlidingWindow.v
module SlidingWindow #(
    parameter KERNEL_WIDTH = 3,        // Width of the kernel
    parameter KERNEL_HEIGHT = 3,       // Height of the kernel
    parameter DATA_WIDTH = 16,         // Data width
    parameter KERNEL_COEF = 32 * KERNEL_WIDTH * KERNEL_HEIGHT // Concatenated kernel coefficients
)(
    input clk,
    input reset,
    input [KERNEL_HEIGHT*DATA_WIDTH-1:0] data_in,
    output reg [DATA_WIDTH-1:0] data_out
);

    localparam KERNEL_SIZE = KERNEL_WIDTH * KERNEL_HEIGHT;

    reg [DATA_WIDTH-1:0] window[KERNEL_HEIGHT-1:0][KERNEL_WIDTH-1:0]; // Sliding window
    reg [31:0] kernel[KERNEL_HEIGHT-1:0][KERNEL_WIDTH-1:0]; // Kernel coefficients

    // Pipeline registers for intermediate sums
    reg signed [31:0] partial_sum[KERNEL_HEIGHT-1:0][KERNEL_WIDTH-1:0];
    reg signed [31:0] sum_stage1[KERNEL_HEIGHT-1:0];
    reg signed [31:0] sum_stage2;
    integer i, j;


    // Shift register logic to create the sliding window
    always @(posedge clk or posedge reset) begin
        if (reset) begin
            
            // Split the concatenated KERNEL_COEF into a 2D array
            for (i = 0; i < KERNEL_HEIGHT; i = i + 1) begin
                for (j = 0; j < KERNEL_WIDTH; j = j + 1) begin
                    kernel[i][j] <= KERNEL_COEF[32 * (i * KERNEL_WIDTH + j) +: 32];
                end
            end

            // Initialize the sliding window to zeros
            for (i = 0; i < KERNEL_HEIGHT; i = i + 1) begin
                for (j = 0; j < KERNEL_WIDTH; j = j + 1) begin
                    window[i][j] <= 0;
                end
            end

            // Initialize pipeline registers to zero
            for (i = 0; i < KERNEL_HEIGHT; i = i + 1) begin
                for (j = 0; j < KERNEL_WIDTH; j = j + 1) begin
                    partial_sum[i][j] <= 0;
                end
                sum_stage1[i] <= 0;
            end
            sum_stage2 <= 0;
            
        end else begin
            // Shift the window left
            for (i = 0; i < KERNEL_HEIGHT; i = i + 1) begin
                for (j = 1; j < KERNEL_WIDTH; j = j + 1) begin
                    window[i][j-1] <= window[i][j];
                end
            end
            // Load new data into the rightmost column
            for (i = 0; i < KERNEL_HEIGHT; i = i + 1) begin
                window[i][KERNEL_WIDTH-1] <= data_in[(i+1)*DATA_WIDTH-1 -: DATA_WIDTH];
            end

            // Compute partial products in parallel
            for (i = 0; i < KERNEL_HEIGHT; i = i + 1) begin
                for (j = 0; j < KERNEL_WIDTH; j = j + 1) begin
                    partial_sum[i][j] <= window[i][j] * kernel[i][j];
                end
            end

            // Sum the partial products for each row (first pipeline stage)
            for (i = 0; i < KERNEL_HEIGHT; i = i + 1) begin
                sum_stage1[i] <= 0;
                for (j = 0; j < KERNEL_WIDTH; j = j + 1) begin
                    sum_stage1[i] <= sum_stage1[i] + partial_sum[i][j];
                end
            end

            // Sum the row sums to get the final result (second pipeline stage)
            sum_stage2 <= 0;
            for (i = 0; i < KERNEL_HEIGHT; i = i + 1) begin
                sum_stage2 <= sum_stage2 + sum_stage1[i];
            end
        end
    end

    // Output the final sum, truncated to DATA_WIDTH bits
    always @(posedge clk or posedge reset) begin
        if (reset) begin
            data_out <= 0;
        end else begin
            data_out <= sum_stage2[DATA_WIDTH-1:0];
        end
    end

endmodule

TB/SlidingWindow_tb.sv
module SlidingWindow_tb;

  // Parameters
  parameter KERNEL_WIDTH = 3;
  parameter KERNEL_HEIGHT = 3;
  parameter DATA_WIDTH = 16;
  parameter KERNEL_COEF = 288'h000100020003000400050006000700080009000A000B000C000D000E000F001000110012;

  // Inputs
  reg clk;
  reg reset;
  reg [KERNEL_WIDTH*DATA_WIDTH-1:0] data_in;

  // Outputs
  wire [DATA_WIDTH-1:0] data_out;

  // Instantiate the Unit Under Test (UUT)
  SlidingWindow #(
    .KERNEL_WIDTH(KERNEL_WIDTH),
    .KERNEL_HEIGHT(KERNEL_HEIGHT),
    .DATA_WIDTH(DATA_WIDTH),
    .KERNEL_COEF(KERNEL_COEF)
  ) uut (
    .clk(clk),
    .reset(reset),
    .data_in(data_in),
    .data_out(data_out)
  );

  integer i, j;
  reg [DATA_WIDTH-1:0] rand_data[KERNEL_HEIGHT-1:0][KERNEL_WIDTH-1:0];

  initial begin
    // Initialize Inputs
    clk = 0;
    reset = 0;
    data_in = 0;

    // Apply reset
    reset = 1;
    #10;
    reset = 0;

    // Test sequence with 100 random inputs
    for (i = 0; i < 100; i = i + 1) begin
      // Generate random data for the sliding window
      for (j = 0; j < KERNEL_HEIGHT; j = j + 1) begin
        rand_data[j][0] = $random;
        rand_data[j][1] = $random;
        rand_data[j][2] = $random;
      end

      data_in = {rand_data[2][2], rand_data[2][1], rand_data[2][0], 
                rand_data[1][2], rand_data[1][1], rand_data[1][0], 
                rand_data[0][2], rand_data[0][1], rand_data[0][0]};
      #10;
    end

    // Finish the simulation
    $finish;
  end

  // Clock generation
  always #5 clk = ~clk;

  // Monitor
  initial begin
    $monitor("Time = %0t, clk = %b, reset = %b, data_in = %h, data_out = %h", 
              $time, clk, reset, data_in, data_out);
  end

  // Add the 2D array to the waveform
  initial begin
    $dumpfile("SlidingWindow_tb.vcd");
    $dumpvars(0, SlidingWindow_tb);
    for (i = 0; i < KERNEL_HEIGHT; i = i + 1) begin
      for (j = 0; j < KERNEL_WIDTH; j = j + 1) begin
        $dumpvars(0, rand_data[i][j]);
      end
    end
  end

endmodule

TB/SlidingWindow_tb.vcd
$date
	Sat Jul 13 13:50:20 2024
$end
$version
	QuestaSim Version 2021.1
$end
$timescale
	1ns
$end

$scope module SlidingWindow_tb $end
$var parameter 32 ! KERNEL_WIDTH $end
$var parameter 32 " KERNEL_HEIGHT $end
$var parameter 32 # DATA_WIDTH $end
$var parameter 288 $ KERNEL_COEF $end
$var reg 1 % clk $end
$var reg 1 & reset $end
$var reg 48 ' data_in [47:0] $end
$var wire 1 ( data_out [15] $end
$var wire 1 ) data_out [14] $end
$var wire 1 * data_out [13] $end
$var wire 1 + data_out [12] $end
$var wire 1 , data_out [11] $end
$var wire 1 - data_out [10] $end
$var wire 1 . data_out [9] $end
$var wire 1 / data_out [8] $end
$var wire 1 0 data_out [7] $end
$var wire 1 1 data_out [6] $end
$var wire 1 2 data_out [5] $end
$var wire 1 3 data_out [4] $end
$var wire 1 4 data_out [3] $end
$var wire 1 5 data_out [2] $end
$var wire 1 6 data_out [1] $end
$var wire 1 7 data_out [0] $end
$var integer 32 8 i $end
$var integer 32 9 j $end

$scope module uut $end
$var parameter 32 : KERNEL_WIDTH $end
$var parameter 32 ; KERNEL_HEIGHT $end
$var parameter 32 < DATA_WIDTH $end
$var parameter 288 = KERNEL_COEF $end
$var parameter 32 > KERNEL_SIZE $end
$var wire 1 ? clk $end
$var wire 1 @ reset $end
$var wire 1 A data_in [47] $end
$var wire 1 B data_in [46] $end
$var wire 1 C data_in [45] $end
$var wire 1 D data_in [44] $end
$var wire 1 E data_in [43] $end
$var wire 1 F data_in [42] $end
$var wire 1 G data_in [41] $end
$var wire 1 H data_in [40] $end
$var wire 1 I data_in [39] $end
$var wire 1 J data_in [38] $end
$var wire 1 K data_in [37] $end
$var wire 1 L data_in [36] $end
$var wire 1 M data_in [35] $end
$var wire 1 N data_in [34] $end
$var wire 1 O data_in [33] $end
$var wire 1 P data_in [32] $end
$var wire 1 Q data_in [31] $end
$var wire 1 R data_in [30] $end
$var wire 1 S data_in [29] $end
$var wire 1 T data_in [28] $end
$var wire 1 U data_in [27] $end
$var wire 1 V data_in [26] $end
$var wire 1 W data_in [25] $end
$var wire 1 X data_in [24] $end
$var wire 1 Y data_in [23] $end
$var wire 1 Z data_in [22] $end
$var wire 1 [ data_in [21] $end
$var wire 1 \ data_in [20] $end
$var wire 1 ] data_in [19] $end
$var wire 1 ^ data_in [18] $end
$var wire 1 _ data_in [17] $end
$var wire 1 ` data_in [16] $end
$var wire 1 a data_in [15] $end
$var wire 1 b data_in [14] $end
$var wire 1 c data_in [13] $end
$var wire 1 d data_in [12] $end
$var wire 1 e data_in [11] $end
$var wire 1 f data_in [10] $end
$var wire 1 g data_in [9] $end
$var wire 1 h data_in [8] $end
$var wire 1 i data_in [7] $end
$var wire 1 j data_in [6] $end
$var wire 1 k data_in [5] $end
$var wire 1 l data_in [4] $end
$var wire 1 m data_in [3] $end
$var wire 1 n data_in [2] $end
$var wire 1 o data_in [1] $end
$var wire 1 p data_in [0] $end
$var reg 16 q data_out [15:0] $end
$var reg 32 r sum_stage2 [31:0] $end
$var integer 32 s i $end
$var integer 32 t j $end
$upscope $end
$upscope $end
$enddefinitions $end
#0
$dumpvars
0%
1&
b0 '
b0 q
b0 r
b11 !
b11 "
b10000 #
b100000000000000100000000000000011000000000000010000000000000001010000000000000110000000000000011100000000000010000000000000001001000000000000101000000000000010110000000000001100000000000000110100000000000011100000000000001111000000000001000000000000000100010000000000010010 $
b11 :
b11 ;
b10000 <
b100000000000000100000000000000011000000000000010000000000000001010000000000000110000000000000011100000000000010000000000000001001000000000000101000000000000010110000000000001100000000000000110100000000000011100000000000001111000000000001000000000000000100010000000000010010 =
b1001 >
b11 s
b11 t
b11 8
b11 9
07
06
05
04
03
02
01
00
0/
0.
0-
0,
0+
0*
0)
0(
0p
0o
0n
0m
0l
0k
0j
0i
0h
0g
0f
0e
0d
0c
0b
0a
0`
0_
0^
0]
0\
0[
0Z
0Y
0X
0W
0V
0U
0T
0S
0R
0Q
0P
0O
0N
0M
0L
0K
0J
0I
0H
0G
0F
0E
0D
0C
0B
0A
1@
0?
$end
#5
1%
1?
b0 s
b0 t
b1 t
b10 t
b11 t
b1 s
b0 t
b1 t
b10 t
b11 t
b10 s
b0 t
b1 t
b10 t
b11 t
b11 s
b0 s
b0 t
b1 t
b10 t
b11 t
b1 s
b0 t
b1 t
b10 t
b11 t
b10 s
b0 t
b1 t
b10 t
b11 t
b11 s
b0 s
b0 t
b1 t
b10 t
b11 t
b1 s
b0 t
b1 t
b10 t
b11 t
b10 s
b0 t
b1 t
b10 t
b11 t
b11 s
#10
0&
b0 8
b0 9
b1 9
b10 9
b11 9
b110101100000100101011110100000010011010100100100 '
0%
1n
1k
1h
1f
1d
1c
1`
1Y
1W
1V
1U
1T
1R
1P
1M
1G
1F
1D
1B
1A
0@
0?
#15
1%
1?
b0 s
b1 t
b10 t
b11 t
b1 s
b1 t
b10 t
b11 t
b10 s
b1 t
b10 t
b11 t
b11 s
b0 s
b1 s
b10 s
b11 s
b0 s
b0 t
b1 t
b10 t
b11 t
b1 s
b0 t
b1 t
b10 t
b11 t
b10 s
b0 t
b1 t
b10 t
b11 t
b11 s
b0 s
b0 t
b1 t
b10 t
b11 t
b1 s
b0 t
b1 t
b10 t
b11 t
b10 s
b0 t
b1 t
b10 t
b11 t
b11 s
b0 s
b1 s
b10 s
b11 s
#20
b1 8
b0 9
b1 9
b10 9
b11 9
b110011010011110111110001011101101100110100001101 '
0%
1p
1m
0k
1e
0d
0c
1b
1a
0`
1_
1^
1\
1[
1Z
0Y
1X
0W
0V
0U
1S
1Q
1N
1L
1K
1H
0G
1E
0D
0?
#25
1%
1?
b0 s
b1 t
b10 t
b11 t
b1 s
b1 t
b10 t
b11 t
b10 s
b1 t
b10 t
b11 t
b11 s
b0 s
b1 s
b10 s
b11 s
b0 s
b0 t
b1 t
b10 t
b11 t
b1 s
b0 t
b1 t
b10 t
b11 t
b10 s
b0 t
b1 t
b10 t
b11 t
b11 s
b0 s
b0 t
b1 t
b10 t
b11 t
b1 s
b0 t
b1 t
b10 t
b11 t
b10 s
b0 t
b1 t
b10 t
b11 t
b11 s
b0 s
b1 s
b10 s
b11 s
#30
b10 8
b0 9
b1 9
b10 9
b11 9
b110101100001001001110010011101111111011111100101 '
0%
0m
1k
1j
1i
1g
0e
1d
1c
1`
0X
1W
0Q
0P
1O
0N
0M
0K
0H
1G
0E
1D
0?
#35
1%
1?
b0 s
b1 t
b10 t
b11 t
b1 s
b1 t
b10 t
b11 t
b10 s
b1 t
b10 t
b11 t
b11 s
b0 s
b1 s
b10 s
b11 s
b0 s
b0 t
b1 t
b10 t
b11 t
b1 s
b0 t
b1 t
b10 t
b11 t
b10 s
b0 t
b1 t
b10 t
b11 t
b11 s
b0 s
b0 t
b1 t
b10 t
b11 t
b1 s
b0 t
b1 t
b10 t
b11 t
b10 s
b0 t
b1 t
b10 t
b11 t
b11 s
b0 s
b1 s
b10 s
b11 s
#40
b11 8
b0 9
b1 9
b10 9
b11 9
b1001100110010101011000001011010010100010111101 '
0%
1m
1l
0j
0h
0g
0f
1e
0d
0b
0a
0_
1]
0\
0Z
0W
1U
0S
1P
0O
1N
0L
1K
1J
0D
1C
0B
0A
0?
#45
1%
1?
b0 s
b1 t
b10 t
b11 t
b1 s
b1 t
b10 t
b11 t
b10 s
b1 t
b10 t
b11 t
b11 s
b0 s
b1 s
b10 s
b11 s
b0 s
b0 t
b1 t
b10 t
b11 t
b1 s
b0 t
b1 t
b10 t
b11 t
b10 s
b0 t
b1 t
b10 t
b11 t
b11 s
b0 s
b0 t
b1 t
b10 t
b11 t
b1 s
b0 t
b1 t
b10 t
b11 t
b10 s
b0 t
b1 t
b10 t
b11 t
b11 s
b0 s
b1 s
b10 s
b11 s
b10110010110101101110011111111000 r
b10010101100010011111010000001000 r
b11010110000010101010110000010010 r
#50
b100 8
b0 9
b1 9
b10 9
b11 9
b1110000000110110111000000100110011111010010110 '
0%
0p
1o
0m
0k
1g
1f
1d
1_
0^
0]
1\
0[
1S
0R
1Q
1M
0K
0J
0G
0F
1E
1D
0?
#55
1%
1?
b0 s
b1 t
b10 t
b11 t
b1 s
b1 t
b10 t
b11 t
b10 s
b1 t
b10 t
b11 t
b11 s
b0 s
b1 s
b10 s
b11 s
b0 s
b0 t
b1 t
b10 t
b11 t
b1 s
b0 t
b1 t
b10 t
b11 t
b10 s
b0 t
b1 t
b10 t
b11 t
b11 s
b0 s
b0 t
b1 t
b10 t
b11 t
b1 s
b0 t
b1 t
b10 t
b11 t
b10 s
b0 t
b1 t
b10 t
b11 t
b11 s
b0 s
b1 s
b10 s
b11 s
b1010110000010010 q
b0 r
b11110010100101011100101011000000 r
b101110101100010101111001010 r
b1111001010100111111001010011110 r
16
13
1-
1,
1*
1(
#60
b101 8
b0 9
b1 9
b10 9
b11 9
b11001010000101001001001001000110111001011001111 '
0%
1p
1m
0l
1j
0f
0e
1b
0\
1[
1X
0T
0S
1R
0Q
0P
1O
0N
1H
1F
0E
0D
1B
0?
#65
1%
1?
b0 s
b1 t
b10 t
b11 t
b1 s
b1 t
b10 t
b11 t
b10 s
b1 t
b10 t
b11 t
b11 s
b0 s
b1 s
b10 s
b11 s
b0 s
b0 t
b1 t
b10 t
b11 t
b1 s
b0 t
b1 t
b10 t
b11 t
b10 s
b0 t
b1 t
b10 t
b11 t
b11 s
b0 s
b0 t
b1 t
b10 t
b11 t
b1 s
b0 t
b1 t
b10 t
b11 t
b10 s
b0 t
b1 t
b10 t
b11 t
b11 s
b0 s
b1 s
b10 s
b11 s
b0 r
b101100100011011001111111010010 r
b11001010011001000000011000001110 r
b11110010101100001110010101001110 r
b1111001010011110 q
15
14
10
1.
0-
0,
1+
1)
#70
b110 8
b0 9
b1 9
b10 9
b11 9
b11011110101100010010100010011111001101111000 '
0%
0p
0o
0n
1l
1k
0i
1h
1a
0_
1]
0[
1Y
0X
1W
0U
1T
0R
1P
1K
1J
1I
1E
0C
0B
0?
#75
1%
1?
b0 s
b1 t
b10 t
b11 t
b1 s
b1 t
b10 t
b11 t
b10 s
b1 t
b10 t
b11 t
b11 s
b0 s
b1 s
b10 s
b11 s
b0 s
b0 t
b1 t
b10 t
b11 t
b1 s
b0 t
b1 t
b10 t
b11 t
b10 s
b0 t
b1 t
b10 t
b11 t
b11 s
b0 s
b0 t
b1 t
b10 t
b11 t
b1 s
b0 t
b1 t
b10 t
b11 t
b10 s
b0 t
b1 t
b10 t
b11 t
b11 s
b0 s
b1 s
b10 s
b11 s
b1110010101001110 q
b0 r
b10110111100001011100110011011000 r
b10101100111111101011101000100110 r
b10010010011100110010010011001000 r
03
11
00
1/
0.
1-
0+
#80
b111 8
b0 9
b1 9
b10 9
b11 9
b10101010100111101000001100001011011111001110001 '
0%
1p
0m
0h
1f
1e
0b
1^
0]
1X
0W
0T
1R
1N
0K
0I
0E
1D
1B
0?
#85
1%
1?
b0 s
b1 t
b10 t
b11 t
b1 s
b1 t
b10 t
b11 t
b10 s
b1 t
b10 t
b11 t
b11 s
b0 s
b1 s
b10 s
b11 s
b0 s
b0 t
b1 t
b10 t
b11 t
b1 s
b0 t
b1 t
b10 t
b11 t
b10 s
b0 t
b1 t
b10 t
b11 t
b11 s
b0 s
b0 t
b1 t
b10 t
b11 t
b1 s
b0 t
b1 t
b10 t
b11 t
b10 s
b0 t
b1 t
b10 t
b11 t
b11 s
b0 s
b1 s
b10 s
b11 s
b0 r
b10000100111010010111100010000110 r
b1010101010010111011101000111000 r
b1101010010000101101010001011100 r
b10010011001000 q
06
05
10
0/
0)
0(
#90
b1000 8
b0 9
b1 9
b10 9
b11 9
b10101011001111111111011010011000000011101100010 '
0%
0p
1o
0l
1h
0e
0d
0c
0a
0`
1]
1Z
0Y
1W
1U
1T
1S
1Q
1L
0J
1I
0?
#95
1%
1?
b0 s
b1 t
b10 t
b11 t
b1 s
b1 t
b10 t
b11 t
b10 s
b1 t
b10 t
b11 t
b11 s
b0 s
b1 s
b10 s
b11 s
b0 s
b0 t
b1 t
b10 t
b11 t
b1 s
b0 t
b1 t
b10 t
b11 t
b10 s
b0 t
b1 t
b10 t
b11 t
b11 s
b0 s
b0 t
b1 t
b10 t
b11 t
b1 s
b0 t
b1 t
b10 t
b11 t
b10 s
b0 t
b1 t
b10 t
b11 t
b11 s
b0 s
b1 s
b10 s
b11 s
b1101010001011100 q
b0 r
b110001010000100110111101101100 r
b101101000100101011001011100100 r
b10100111000111010100111000000100 r
15
13
00
1+
0*
1)
1(
#100
b1001 8
b0 9
b1 9
b10 9
b11 9
b1111101101000000110010010010010011011110001001 '
0%
1p
0o
1m
0k
0j
1i
1d
1c
1`
0^
0X
0U
0R
0Q
0P
0O
0N
0M
1J
0H
1G
1E
1C
0B
0?
#105
1%
1?
b0 s
b1 t
b10 t
b11 t
b1 s
b1 t
b10 t
b11 t
b10 s
b1 t
b10 t
b11 t
b11 s
b0 s
b1 s
b10 s
b11 s
b0 s
b0 t
b1 t
b10 t
b11 t
b1 s
b0 t
b1 t
b10 t
b11 t
b10 s
b0 t
b1 t
b10 t
b11 t
b11 s
b0 s
b0 t
b1 t
b10 t
b11 t
b1 s
b0 t
b1 t
b10 t
b11 t
b10 s
b0 t
b1 t
b10 t
b11 t
b11 s
b0 s
b1 s
b10 s
b11 s
b0 r
b11001011010000100011100110100100 r
b11101011101011001100000011010100 r
b11110001111000101110001110000010 r
b100111000000100 q
04
03
01
1.
1,
0+
0(
#110
b1010 8
b0 9
b1 9
b10 9
b11 9
b110110110001001011101101001111010101101001110111 '
0%
1o
1n
0m
1l
1k
1j
0i
0h
0f
1e
0c
1b
1^
1\
1[
0Z
1X
0W
1V
1U
0T
1R
1Q
1O
0J
0I
1H
0F
0C
1B
1A
0?
#115
1%
1?
b0 s
b1 t
b10 t
b11 t
b1 s
b1 t
b10 t
b11 t
b10 s
b1 t
b10 t
b11 t
b11 s
b0 s
b1 s
b10 s
b11 s
b0 s
b0 t
b1 t
b10 t
b11 t
b1 s
b0 t
b1 t
b10 t
b11 t
b10 s
b0 t
b1 t
b10 t
b11 t
b11 s
b0 s
b0 t
b1 t
b10 t
b11 t
b1 s
b0 t
b1 t
b10 t
b11 t
b10 s
b0 t
b1 t
b10 t
b11 t
b11 s
b0 s
b1 s
b10 s
b11 s
b1110001110000010 q
b0 r
b11000001110011110011100101010000 r
b1000101110110001001111010 r
b10010001111110000010001110011110 r
16
05
10
1/
0-
0,
1*
1(
#120
b1011 8
b0 9
b1 9
b10 9
b11 9
b10010110100100101011001010110111000100001111000 '
0%
0p
0o
0n
1m
0g
0d
0b
1a
1_
0^
0[
1Z
0V
1T
0S
0Q
1P
0O
1M
0L
1J
0D
0A
0?
#125
1%
1?
b0 s
b1 t
b10 t
b11 t
b1 s
b1 t
b10 t
b11 t
b10 s
b1 t
b10 t
b11 t
b11 s
b0 s
b1 s
b10 s
b11 s
b0 s
b0 t
b1 t
b10 t
b11 t
b1 s
b0 t
b1 t
b10 t
b11 t
b10 s
b0 t
b1 t
b10 t
b11 t
b11 s
b0 s
b0 t
b1 t
b10 t
b11 t
b1 s
b0 t
b1 t
b10 t
b11 t
b10 s
b0 t
b1 t
b10 t
b11 t
b11 s
b0 s
b1 s
b10 s
b11 s
b0 r
b11000001110111101110000011001000 r
b10000000010010000111110011110110 r
b10000111101011010000111011111000 r
b10001110011110 q
15
14
13
0)
0(
#130
b1100 8
b0 9
b1 9
b10 9
b11 9
b101110111001110111100001001101001100111111010 '
0%
1o
1i
1h
1d
0`
1^
0]
0\
1[
0Z
0X
1V
1S
0R
1Q
1O
0M
1L
1K
1F
0E
1D
0B
0?
#135
1%
1?
b0 s
b1 t
b10 t
b11 t
b1 s
b1 t
b10 t
b11 t
b10 s
b1 t
b10 t
b11 t
b11 s
b0 s
b1 s
b10 s
b11 s
b0 s
b0 t
b1 t
b10 t
b11 t
b1 s
b0 t
b1 t
b10 t
b11 t
b10 s
b0 t
b1 t
b10 t
b11 t
b11 s
b0 s
b0 t
b1 t
b10 t
b11 t
b1 s
b0 t
b1 t
b10 t
b11 t
b10 s
b0 t
b1 t
b10 t
b11 t
b11 s
b0 s
b1 s
b10 s
b11 s
b111011111000 q
b0 r
b10001001100010111101010110100000 r
b11010101111111011111101010011000 r
b10111100001100100111011111110010 r
06
05
12
11
0/
1-
1,
0*
#140
b1101 8
b0 9
b1 9
b10 9
b11 9
b110110110101101000011010111001100011011011001011 '
0%
1p
0l
0k
0h
1g
1f
0e
1c
0a
1Z
1Y
1W
0V
0S
0Q
0P
1M
0K
0F
1E
1B
1A
0?
#145
1%
1?
b0 s
b1 t
b10 t
b11 t
b1 s
b1 t
b10 t
b11 t
b10 s
b1 t
b10 t
b11 t
b11 s
b0 s
b1 s
b10 s
b11 s
b0 s
b0 t
b1 t
b10 t
b11 t
b1 s
b0 t
b1 t
b10 t
b11 t
b10 s
b0 t
b1 t
b10 t
b11 t
b11 s
b0 s
b0 t
b1 t
b10 t
b11 t
b1 s
b0 t
b1 t
b10 t
b11 t
b10 s
b0 t
b1 t
b10 t
b11 t
b11 s
b0 s
b1 s
b10 s
b11 s
b0 r
b1010110001000010011000100011100 r
b10000111001101011100110101111010 r
b11001011110010111001011100010000 r
b111011111110010 q
16
04
1/
0,
1+
1*
1)
#150
b1110 8
b0 9
b1 9
b10 9
b11 9
b11001101000011111111010001000001100101111001 '
0%
0o
1l
1k
0i
1h
0g
0f
1e
0c
0_
0[
0Y
1X
1V
1S
1R
1Q
0O
0M
1I
0H
0G
1F
0D
0B
0A
0?
#155
1%
1?
b0 s
b1 t
b10 t
b11 t
b1 s
b1 t
b10 t
b11 t
b10 s
b1 t
b10 t
b11 t
b11 s
b0 s
b1 s
b10 s
b11 s
b0 s
b0 t
b1 t
b10 t
b11 t
b1 s
b0 t
b1 t
b10 t
b11 t
b10 s
b0 t
b1 t
b10 t
b11 t
b11 s
b0 s
b0 t
b1 t
b10 t
b11 t
b1 s
b0 t
b1 t
b10 t
b11 t
b10 s
b0 t
b1 t
b10 t
b11 t
b11 s
b0 s
b1 s
b10 s
b11 s
b1001011100010000 q
b0 r
b1010011110110011100011011001010 r
b1000010011101011011101110000 r
b100110101011100100110011000000 r
06
02
01
00
0*
0)
1(
#160
b1111 8
b0 9
b1 9
b10 9
b11 9
b111010010100111011101101010101100000001011000011 '
0%
1o
0m
0l
0k
1i
0h
1g
0e
0d
1_
1\
0W
0T
1O
1N
1M
0L
0I
1H
0F
1C
1B
1A
0?
#165
1%
1?
b0 s
b1 t
b10 t
b11 t
b1 s
b1 t
b10 t
b11 t
b10 s
b1 t
b10 t
b11 t
b11 s
b0 s
b1 s
b10 s
b11 s
b0 s
b0 t
b1 t
b10 t
b11 t
b1 s
b0 t
b1 t
b10 t
b11 t
b10 s
b0 t
b1 t
b10 t
b11 t
b11 s
b0 s
b0 t
b1 t
b10 t
b11 t
b1 s
b0 t
b1 t
b10 t
b11 t
b10 s
b0 t
b1 t
b10 t
b11 t
b11 s
b0 s
b1 s
b10 s
b11 s
b0 r
b10000000011101101110100000100110 r
b10001000010000010100111001010000 r
b10011001000001000011000101010110 r
b100110011000000 q
03
11
10
0/
0.
1,
0+
1)
0(
#170
b10000 8
b0 9
b1 9
b10 9
b11 9
b1011000000010001011101100100111011111110010100 '
0%
0p
0o
1n
1l
0j
1h
1f
1e
1d
1c
1a
1`
0^
0Z
1Y
1T
0S
0Q
0O
0M
0J
0H
1F
0B
0A
0?
#175
1%
1?
b0 s
b1 t
b10 t
b11 t
b1 s
b1 t
b10 t
b11 t
b10 s
b1 t
b10 t
b11 t
b11 s
b0 s
b1 s
b10 s
b11 s
b0 s
b0 t
b1 t
b10 t
b11 t
b1 s
b0 t
b1 t
b10 t
b11 t
b10 s
b0 t
b1 t
b10 t
b11 t
b11 s
b0 s
b0 t
b1 t
b10 t
b11 t
b1 s
b0 t
b1 t
b10 t
b11 t
b10 s
b0 t
b1 t
b10 t
b11 t
b11 s
b0 s
b1 s
b10 s
b11 s
b11000101010110 q
b0 r
b10111011000111101100101111010110 r
b10110110111000100000101000010110 r
b11100110101101011100110010100000 r
16
15
13
00
1/
0-
0,
1+
1*
0)
#180
b10001 8
b0 9
b1 9
b10 9
b11 9
b11100011001010100101101101101100100100111001010 '
0%
1o
0n
1m
0l
1j
0g
0f
0d
0c
1b
0a
0`
1^
1[
0T
1S
0R
1P
1L
1I
1H
0F
0E
1D
1B
0?
#185
1%
1?
b0 s
b1 t
b10 t
b11 t
b1 s
b1 t
b10 t
b11 t
b10 s
b1 t
b10 t
b11 t
b11 s
b0 s
b1 s
b10 s
b11 s
b0 s
b0 t
b1 t
b10 t
b11 t
b1 s
b0 t
b1 t
b10 t
b11 t
b10 s
b0 t
b1 t
b10 t
b11 t
b11 s
b0 s
b0 t
b1 t
b10 t
b11 t
b1 s
b0 t
b1 t
b10 t
b11 t
b10 s
b0 t
b1 t
b10 t
b11 t
b11 s
b0 s
b1 s
b10 s
b11 s
b0 r
b1010011111101101100101110111110 r
b11111111011101111001111110000000 r
b1000001001101111000000110001010 r
b1100110010100000 q
06
05
03
12
01
10
0/
1-
1,
0+
0*
1)
1(
#190
b10010 8
b0 9
b1 9
b10 9
b11 9
b1100001100011100000100001011011101100100101000 '
0%
0o
1k
0j
0i
1d
1a
1`
0_
1]
0\
0Y
0X
0U
0S
1O
0L
1J
0H
0B
0?
#195
1%
1?
b0 s
b1 t
b10 t
b11 t
b1 s
b1 t
b10 t
b11 t
b10 s
b1 t
b10 t
b11 t
b11 s
b0 s
b1 s
b10 s
b11 s
b0 s
b0 t
b1 t
b10 t
b11 t
b1 s
b0 t
b1 t
b10 t
b11 t
b10 s
b0 t
b1 t
b10 t
b11 t
b11 s
b0 s
b0 t
b1 t
b10 t
b11 t
b1 s
b0 t
b1 t
b10 t
b11 t
b10 s
b0 t
b1 t
b10 t
b11 t
b11 s
b0 s
b1 s
b10 s
b11 s
b1000000110001010 q
b0 r
b11010010010111111010011101010010 r
b11010111010110101011111100011010 r
b10000101000010010000100100010000 r
16
14
02
1/
0-
0,
0)
#200
b10011 8
b0 9
b1 9
b10 9
b11 9
b110001100011110100001000110110100110011110000110 '
0%
1o
1n
0m
0k
1i
1g
1f
0e
0d
1c
0a
0`
1_
0^
1\
0[
1Z
1Y
0V
1U
0O
1M
1L
1K
0J
0I
1G
1F
0D
0C
1B
1A
0?
#205
1%
1?
b0 s
b1 t
b10 t
b11 t
b1 s
b1 t
b10 t
b11 t
b10 s
b1 t
b10 t
b11 t
b11 s
b0 s
b1 s
b10 s
b11 s
b0 s
b0 t
b1 t
b10 t
b11 t
b1 s
b0 t
b1 t
b10 t
b11 t
b10 s
b0 t
b1 t
b10 t
b11 t
b11 s
b0 s
b0 t
b1 t
b10 t
b11 t
b1 s
b0 t
b1 t
b10 t
b11 t
b10 s
b0 t
b1 t
b10 t
b11 t
b11 s
b0 s
b1 s
b10 s
b11 s
b0 r
b11010000101111111010100011110000 r
b10101010001101000011001100111000 r
b11110100110111101110100010011110 r
b100100010000 q
06
04
13
00
1,
0(
#210
b10100 8
b0 9
b1 9
b10 9
b11 9
b1011100111110110000110100000010111010101 '
0%
1p
0o
1l
1j
0g
0c
0b
0Z
0Y
1W
1V
0U
1T
1S
1R
1Q
0N
1I
0G
0F
0B
0A
0?
#215
1%
1?
b0 s
b1 t
b10 t
b11 t
b1 s
b1 t
b10 t
b11 t
b10 s
b1 t
b10 t
b11 t
b11 s
b0 s
b1 s
b10 s
b11 s
b0 s
b0 t
b1 t
b10 t
b11 t
b1 s
b0 t
b1 t
b10 t
b11 t
b10 s
b0 t
b1 t
b10 t
b11 t
b11 s
b0 s
b0 t
b1 t
b10 t
b11 t
b1 s
b0 t
b1 t
b10 t
b11 t
b10 s
b0 t
b1 t
b10 t
b11 t
b11 s
b0 s
b1 s
b10 s
b11 s
b1110100010011110 q
b0 r
b11111111110110111001000110001010 r
b1011010000001011000000001110110 r
b11010110010010101010101101010110 r
16
15
14
10
0/
1*
1)
1(
#220
b10101 8
b0 9
b1 9
b10 9
b11 9
b111111110111100001010111100001100000111111011100 '
0%
0p
1m
1g
1e
1^
0]
0\
1Y
1X
0S
0Q
0P
1J
0I
1H
1G
1F
1E
1D
1C
1B
1A
0?
